hdxpop/__init__.py
hdxpop/hdxpop.py
hdxpop-0.0.4.dist-info/LICENSE
hdxpop-0.0.4.dist-info/METADATA
hdxpop-0.0.4.dist-info/WHEEL
hdxpop-0.0.4.dist-info/entry_points.txt
hdxpop-0.0.4.dist-info/top_level.txt
hdxpop-0.0.4.dist-info/RECORD
