Metadata-Version: 2.1
Name: hdxpop
Version: 0.0.4
Summary: Simple tool to download High Resolution Population Density Maps from Humanitarian Data Exchange
Home-page: https://github.com/samapriya/hdxpop
Author: Samapriya Roy
Author-email: samapriya.roy@gmail.com
License: MIT License
Platform: UNKNOWN
Classifier: Development Status :: 3 - Alpha
Classifier: Intended Audience :: Developers
Classifier: Intended Audience :: Science/Research
Classifier: Natural Language :: English
Classifier: License :: OSI Approved :: Apache Software License
Classifier: Programming Language :: Python :: 3
Classifier: Programming Language :: Python :: 3.6
Classifier: Programming Language :: Python :: 3.7
Classifier: Programming Language :: Python :: 3.8
Classifier: Operating System :: OS Independent
Classifier: Topic :: Scientific/Engineering :: GIS
Requires-Python: >=3.2
Requires-Dist: requests (>=2.21.1)
Requires-Dist: beautifulsoup4 (>=4.8.2)
